{
    "Scientific Name": "carex eburnea ",
    "Common Name": "bristle-leaved sedge",
    "Type": "Rush or Sedge",
    "Family": "Cyperaceae",
    "Native Range": "Eastern and central North America",
    "Zone": "2 to 8",
    "Height": "0.50 to 1.00 feet",
    "Spread": "0.50 to 1.00 feet",
    "Bloom Time": "April",
    "Bloom Description": "Green",
    "Sun": "Part shade to full shade",
    "Water": "Medium",
    "Maintenance": "Low",
    "Suggested Use": "Ground Cover, Naturalize",
    "Flower": "Insignificant",
    "Tolerate": "Deer, Heavy Shade"
}